nbdev_cards/__init__.py
nbdev_cards/_modidx.py
nbdev_cards/card.py
nbdev_cards/deck.py
nbdev_cards_31082022-0.0.1.dist-info/LICENSE
nbdev_cards_31082022-0.0.1.dist-info/METADATA
nbdev_cards_31082022-0.0.1.dist-info/WHEEL
nbdev_cards_31082022-0.0.1.dist-info/entry_points.txt
nbdev_cards_31082022-0.0.1.dist-info/top_level.txt
nbdev_cards_31082022-0.0.1.dist-info/RECORD
